odoo/addons/mrp_production_split/README.rst
odoo/addons/mrp_production_split/__init__.py
odoo/addons/mrp_production_split/__manifest__.py
odoo/addons/mrp_production_split/i18n/de.po
odoo/addons/mrp_production_split/i18n/es.po
odoo/addons/mrp_production_split/i18n/it.po
odoo/addons/mrp_production_split/i18n/mrp_production_split.pot
odoo/addons/mrp_production_split/models/__init__.py
odoo/addons/mrp_production_split/models/mrp_production.py
odoo/addons/mrp_production_split/readme/CONTRIBUTORS.rst
odoo/addons/mrp_production_split/readme/DESCRIPTION.rst
odoo/addons/mrp_production_split/readme/USAGE.rst
odoo/addons/mrp_production_split/security/ir.model.access.csv
odoo/addons/mrp_production_split/static/description/icon.png
odoo/addons/mrp_production_split/static/description/index.html
odoo/addons/mrp_production_split/templates/messages.xml
odoo/addons/mrp_production_split/tests/__init__.py
odoo/addons/mrp_production_split/tests/common.py
odoo/addons/mrp_production_split/tests/test_mrp_production_split.py
odoo/addons/mrp_production_split/views/mrp_production.xml
odoo/addons/mrp_production_split/wizards/__init__.py
odoo/addons/mrp_production_split/wizards/mrp_production_split_wizard.py
odoo/addons/mrp_production_split/wizards/mrp_production_split_wizard.xml
odoo_addon_mrp_production_split-15.0.1.0.0.12.dist-info/METADATA
odoo_addon_mrp_production_split-15.0.1.0.0.12.dist-info/WHEEL
odoo_addon_mrp_production_split-15.0.1.0.0.12.dist-info/top_level.txt
odoo_addon_mrp_production_split-15.0.1.0.0.12.dist-info/RECORD
